security_md/__init__.py
security_md/cli.py
security_md/py.typed
security_md-1.0.0.dist-info/LICENSE
security_md-1.0.0.dist-info/METADATA
security_md-1.0.0.dist-info/WHEEL
security_md-1.0.0.dist-info/entry_points.txt
security_md-1.0.0.dist-info/RECORD
