Metadata-Version: 2.1
Name: security.md
Version: 1.0.0
Summary: Common utilities for Camptocamp CI
Home-page: https://github.com/camptocamp/c2cciutils
License: FreeBSD
Keywords: ci
Author: Camptocamp
Author-email: info@camptocamp.com
Requires-Python: >=3.9
Classifier: Development Status :: 5 - Production/Stable
Classifier: Intended Audience :: Developers
Classifier: License :: OSI Approved :: BSD License
Classifier: License :: Other/Proprietary License
Classifier: Operating System :: OS Independent
Classifier: Programming Language :: Python
Classifier: Programming Language :: Python :: 3
Classifier: Programming Language :: Python :: 3.9
Classifier: Programming Language :: Python :: 3.10
Classifier: Programming Language :: Python :: 3.11
Classifier: Programming Language :: Python :: 3.12
Classifier: Programming Language :: Python :: 3.13
Classifier: Typing :: Typed
Requires-Dist: defusedxml (>=0.0.0,<1.0.0)
Requires-Dist: markdown (>=3.0,<4.0)
Requires-Dist: markdown-table (>=2020.0.0,<2021.0.0)
Project-URL: Repository, https://github.com/camptocamp/c2cciutils
